dbcleanup/__init__.py
dbcleanup/admin.py
dbcleanup/apps.py
dbcleanup/models.py
dbcleanup/utils.py
dbcleanup/management/__init__.py
dbcleanup/management/commands/__init__.py
dbcleanup/management/commands/dbcleanup.py
django_dbcleanup-0.1.5.dist-info/licenses/LICENSE
django_dbcleanup-0.1.5.dist-info/METADATA
django_dbcleanup-0.1.5.dist-info/WHEEL
django_dbcleanup-0.1.5.dist-info/top_level.txt
django_dbcleanup-0.1.5.dist-info/RECORD
