Metadata-Version: 2.4
Name: django-dbcleanup
Version: 0.1.5
Summary: Easily monitor database usage - and clean it up (based on your django models)
Home-page: https://github.com/surface-security/django-dbcleanup/
Author: PPB - InfoSec Engineering
Author-email: surface@paddypowerbetfair.com
License: MIT
Classifier: Development Status :: 5 - Production/Stable
Classifier: Framework :: Django
Classifier: License :: OSI Approved :: MIT License
Classifier: Intended Audience :: Developers
Classifier: Operating System :: OS Independent
Classifier: Programming Language :: Python
Classifier: Programming Language :: Python :: 3.7
Classifier: Programming Language :: Python :: 3.9
Classifier: Programming Language :: Python :: 3.11
Classifier: Environment :: Web Environment
Classifier: Topic :: Software Development
Requires-Python: >=3.7
License-File: LICENSE
Requires-Dist: Django<6.0,>=3.0
Dynamic: license-file
